piltext/__init__.py
piltext/_version.py
piltext/ascii_art.py
piltext/cli.py
piltext/config_exporter.py
piltext/config_loader.py
piltext/font_manager.py
piltext/image_dial.py
piltext/image_drawer.py
piltext/image_handler.py
piltext/image_plot.py
piltext/image_squares.py
piltext/py.typed
piltext/text_box.py
piltext/text_grid.py
piltext-0.5.0.dist-info/licenses/LICENSE
piltext-0.5.0.dist-info/METADATA
piltext-0.5.0.dist-info/WHEEL
piltext-0.5.0.dist-info/entry_points.txt
piltext-0.5.0.dist-info/top_level.txt
piltext-0.5.0.dist-info/RECORD
