Metadata-Version: 2.4
Name: piltext
Version: 0.5.0
Summary: Creates PNG from text using Pillow
Author-email: Holger Nahrstaedt <nahrstaedt@gmail.com>
License: MIT License
Project-URL: Homepage, https://github.com/holgern/piltext
Keywords: Pillow,png,PIL
Classifier: Intended Audience :: Developers
Classifier: License :: OSI Approved :: MIT License
Classifier: Operating System :: OS Independent
Classifier: Programming Language :: Python :: 3
Classifier: Programming Language :: Python :: 3.9
Classifier: Programming Language :: Python :: 3.10
Classifier: Programming Language :: Python :: 3.11
Classifier: Programming Language :: Python :: 3.12
Classifier: Topic :: Software Development :: Libraries
Requires-Python: >3.8.0
License-File: LICENSE
Requires-Dist: Pillow
Requires-Dist: typer
Requires-Dist: tomli>=1.2.0; python_version < "3.11"
Requires-Dist: tomli-w>=1.0.0
Requires-Dist: rich-pixels
Dynamic: license-file
